cfficloak/__init__.py
cfficloak/__version__.py
cfficloak/arrays.py
cfficloak/cobject.py
cfficloak/cstruct.py
cfficloak/endian_conversion.py
cfficloak/enums.py
cfficloak/ffi.py
cfficloak/functions.py
cfficloak/patches.py
cfficloak/typedef.py
cfficloak/wrap.py
cfficloak/builder/__init__.py
cfficloak/builder/third-party/pcpp/__init__.py
cfficloak/builder/third-party/pcpp/cmd.py
cfficloak/builder/third-party/pcpp/preprocessor.py
cfficloak/builder/third-party/ply/__init__.py
cfficloak/builder/third-party/ply/cpp.py
cfficloak/builder/third-party/ply/ctokens.py
cfficloak/builder/third-party/ply/lex.py
cfficloak/builder/third-party/ply/yacc.py
cfficloak/builder/third-party/ply/ygen.py
cfficloak-2.8.dist-info/LICENSE.apache-2.0.txt
cfficloak-2.8.dist-info/LICENSE.txt
cfficloak-2.8.dist-info/METADATA
cfficloak-2.8.dist-info/WHEEL
cfficloak-2.8.dist-info/top_level.txt
cfficloak-2.8.dist-info/RECORD
