Metadata-Version: 2.2
Name: cfficloak
Version: 2.8
Summary: A simple but flexible module for creating object-oriented, pythonic CFFI wrappers.
Author-email: Andrew Leech <andrew@alelec.net>
License: 
Classifier: License :: OSI Approved :: Apache Software License
Classifier: Programming Language :: Python :: 3
License-File: LICENSE.apache-2.0.txt
License-File: LICENSE.txt
Requires-Dist: six
Requires-Dist: wrapt
Provides-Extra: cffi
Requires-Dist: cffi>=1.6; extra == "cffi"
Provides-Extra: test
Requires-Dist: cffi>=1.6; extra == "test"
Requires-Dist: setuptools; extra == "test"
Requires-Dist: setuptools_bin_targets; extra == "test"
Requires-Dist: pytest; extra == "test"
Requires-Dist: pytest-runner; extra == "test"
Requires-Dist: pytest-cov; extra == "test"
Requires-Dist: numpy; extra == "test"
Provides-Extra: build
Requires-Dist: ply; extra == "build"
Requires-Dist: pcpp; extra == "build"
Requires-Dist: cffi>=1.6; extra == "build"
